setup.py
Scarf_shop.egg-info/PKG-INFO
Scarf_shop.egg-info/SOURCES.txt
Scarf_shop.egg-info/dependency_links.txt
Scarf_shop.egg-info/top_level.txt
scarf/__init__.py
scarf/scarf.py
scarf/ThreadManager/__init__.py
scarf/ThreadManager/pool.py
scarf/main/Reslove_Request.py
scarf/main/__init__.py
scarf/main/dbPool.py
scarf/main/main.py
scarf/main/ws.py