Metadata-Version: 1.0
Name: Scarf-shop
Version: 0.0.1
Summary: Easy And Fast To Craete A HTTP Server
Home-page: https://github.com/Mate8/Scarf
Author: cheng_qi
Author-email: sdfsdvdac@qq.com
License: MIT License
Platform: UNKNOWN
